Random_decimal/Random_decimal .py
Random_decimal/__init__.py
Random_decimal-1.3.0.dist-info/LICENSE
Random_decimal-1.3.0.dist-info/METADATA
Random_decimal-1.3.0.dist-info/WHEEL
Random_decimal-1.3.0.dist-info/top_level.txt
Random_decimal-1.3.0.dist-info/RECORD
